{
  "version": "7",
  "dialect": "mysql",
  "entries": [
    {
      "idx": 0,
      "version": "5",
      "when": 1768346024433,
      "tag": "0000_smart_venom",
      "breakpoints": true
    },
    {
      "idx": 1,
      "version": "5",
      "when": 1768346073420,
      "tag": "0001_graceful_paibok",
      "breakpoints": true
    },
    {
      "idx": 2,
      "version": "5",
      "when": 1769333965202,
      "tag": "0002_lethal_mimic",
      "breakpoints": true
    },
    {
      "idx": 3,
      "version": "5",
      "when": 1771360005593,
      "tag": "0003_unknown_shriek",
      "breakpoints": true
    },
    {
      "idx": 4,
      "version": "5",
      "when": 1773248595575,
      "tag": "0004_sloppy_invisible_woman",
      "breakpoints": true
    },
    {
      "idx": 5,
      "version": "5",
      "when": 1773248827460,
      "tag": "0005_long_major_mapleleaf",
      "breakpoints": true
    },
    {
      "idx": 6,
      "version": "5",
      "when": 1773862689261,
      "tag": "0006_easy_viper",
      "breakpoints": true
    }
  ]
}